odoo/addons/mrp_order_report_lot_barcode/README.rst
odoo/addons/mrp_order_report_lot_barcode/__init__.py
odoo/addons/mrp_order_report_lot_barcode/__manifest__.py
odoo/addons/mrp_order_report_lot_barcode/i18n/it.po
odoo/addons/mrp_order_report_lot_barcode/i18n/mrp_order_report_lot_barcode.pot
odoo/addons/mrp_order_report_lot_barcode/static/description/icon.png
odoo/addons/mrp_order_report_lot_barcode/views/mrp_order_report_product_barcode.xml
odoo_addon_mrp_order_report_lot_barcode-16.0.1.0.0.3.dist-info/METADATA
odoo_addon_mrp_order_report_lot_barcode-16.0.1.0.0.3.dist-info/WHEEL
odoo_addon_mrp_order_report_lot_barcode-16.0.1.0.0.3.dist-info/top_level.txt
odoo_addon_mrp_order_report_lot_barcode-16.0.1.0.0.3.dist-info/RECORD
