Metadata-Version: 2.1
Name: odoo-addon-mrp_order_report_lot_barcode
Version: 16.0.1.0.0.3
Summary: Lot Barcode on the Production Order
Home-page: https://github.com/OCA/manufacture-reporting
Author: Open Source Integrators,Odoo Community Association (OCA)
Author-email: support@odoo-community.org
License: AGPL-3
Classifier: Programming Language :: Python
Classifier: Framework :: Odoo
Classifier: Framework :: Odoo :: 16.0
Classifier: License :: OSI Approved :: GNU Affero General Public License v3
Requires-Python: >=3.10
Requires-Dist: odoo<16.1dev,>=16.0a
